hug/__init__.py
hug/_async.py
hug/_empty.py
hug/_version.py
hug/api.py
hug/authentication.py
hug/decorators.py
hug/defaults.py
hug/development_runner.py
hug/directives.py
hug/exceptions.py
hug/format.py
hug/input_format.py
hug/interface.py
hug/introspect.py
hug/json_module.py
hug/middleware.py
hug/output_format.py
hug/redirect.py
hug/route.py
hug/routing.py
hug/store.py
hug/test.py
hug/transform.py
hug/types.py
hug/use.py
hug/validate.py
hug_kt-2.4.0.dist-info/METADATA
hug_kt-2.4.0.dist-info/RECORD
hug_kt-2.4.0.dist-info/WHEEL
hug_kt-2.4.0.dist-info/entry_points.txt
hug_kt-2.4.0.dist-info/top_level.txt
